LICENSE
MANIFEST.in
README.md
setup.py
bin/msgflo-python
msgflo/__init__.py
msgflo/msgflo.py
msgflo.egg-info/PKG-INFO
msgflo.egg-info/SOURCES.txt
msgflo.egg-info/dependency_links.txt
msgflo.egg-info/requires.txt
msgflo.egg-info/top_level.txt